{"summary":{"types":["Water"],"species":"Formidable Pokémon","height":"4′11″ (1.50m)","weight":"208.6 lbs (94.6 kg)","abilities":["Torrent","Shell Armor"]},"training":{"EV yield":"3 Special Attack","Catch rate":"45 (5.9% with PokéBall, full HP)","Base Happiness":"70 (normal)","Base EXP":"238","Growth Rate":"Medium Slow"},"breeding":{"Egg Groups":"Field","Gender":"87.5% male, 12.5% female","Egg cycles":"20(base 5,120 steps)"},"stats":{"HP":{"base":"95","min":"300","max":"394"},"Attack":{"base":"100","min":"184","max":"328"},"Defense":{"base":"85","min":"157","max":"295"},"Sp. Atk":{"base":"108","min":"198","max":"346"},"Sp. Def":{"base":"70","min":"130","max":"262"},"Speed":{"base":"70","min":"130","max":"262"}},"entry":{"Black":"One swing of the sword incorporated in its armor can fell an opponent. A simple glare from one of them quiets everybody.","White":"Part of the armor on its anterior legs becomes a giant sword. Its cry alone is enough to intimidate most enemies.","Black 2White 2":"In the time it takes a foe to blink, it can draw and sheathe the seamitars attached to its front legs.","XOmega Ruby":"In the time it takes a foe to blink, it can draw and sheathe the seamitars attached to its front legs.","YAlpha Sapphire":"One swing of the sword incorporated in its armor can fell an opponent. A simple glare from one of them quiets everybody."},"moves":{"byLevelUp":[{"Level":"1","Name":"Megahorn","Type":"Bug","Category":"physical","Power":"120","Accuracy":"85"},{"Level":"1","Name":"Slash","Type":"Normal","Category":"physical","Power":"70","Accuracy":"100"},{"Level":"1","Name":"Tackle","Type":"Normal","Category":"physical","Power":"40","Accuracy":"100"},{"Level":"1","Name":"Tail Whip","Type":"Normal","Category":"status","Power":"—","Accuracy":"100"},{"Level":"1","Name":"Water Gun","Type":"Water","Category":"special","Power":"40","Accuracy":"100"},{"Level":"1","Name":"Water Sport","Type":"Water","Category":"status","Power":"—","Accuracy":"—"},{"Level":"5","Name":"Tail Whip","Type":"Normal","Category":"status","Power":"—","Accuracy":"100"},{"Level":"7","Name":"Water Gun","Type":"Water","Category":"special","Power":"40","Accuracy":"100"},{"Level":"11","Name":"Water Sport","Type":"Water","Category":"status","Power":"—","Accuracy":"—"},{"Level":"13","Name":"Focus Energy","Type":"Normal","Category":"status","Power":"—","Accuracy":"—"},{"Level":"18","Name":"Razor Shell","Type":"Water","Category":"physical","Power":"75","Accuracy":"95"},{"Level":"21","Name":"Fury Cutter","Type":"Bug","Category":"physical","Power":"40","Accuracy":"95"},{"Level":"25","Name":"Water Pulse","Type":"Water","Category":"special","Power":"60","Accuracy":"100"},{"Level":"29","Name":"Revenge","Type":"Fighting","Category":"physical","Power":"60","Accuracy":"100"},{"Level":"34","Name":"Aqua Jet","Type":"Water","Category":"physical","Power":"40","Accuracy":"100"},{"Level":"39","Name":"Encore","Type":"Normal","Category":"status","Power":"—","Accuracy":"100"},{"Level":"46","Name":"Aqua Tail","Type":"Water","Category":"physical","Power":"90","Accuracy":"90"},{"Level":"51","Name":"Retaliate","Type":"Normal","Category":"physical","Power":"70","Accuracy":"100"},{"Level":"58","Name":"Swords Dance","Type":"Normal","Category":"status","Power":"—","Accuracy":"—"},{"Level":"63","Name":"Hydro Pump","Type":"Water","Category":"special","Power":"110","Accuracy":"80"}],"byEgg":[{"Name":"Air Slash","Type":"Flying","Category":"special","Power":"75","Accuracy":"95"},{"Name":"Assurance","Type":"Dark","Category":"physical","Power":"60","Accuracy":"100"},{"Name":"Brine","Type":"Water","Category":"special","Power":"65","Accuracy":"100"},{"Name":"Copycat","Type":"Normal","Category":"status","Power":"—","Accuracy":"—"},{"Name":"Detect","Type":"Fighting","Category":"status","Power":"—","Accuracy":"—"},{"Name":"Night Slash","Type":"Dark","Category":"physical","Power":"70","Accuracy":"100"},{"Name":"Screech","Type":"Normal","Category":"status","Power":"—","Accuracy":"85"},{"Name":"Trump Card","Type":"Normal","Category":"special","Power":"—","Accuracy":"∞"}],"byTutor":[{"Name":"Hydro Cannon","Type":"Water","Category":"special","Power":"150","Accuracy":"90"},{"Name":"Water Pledge","Type":"Water","Category":"special","Power":"80","Accuracy":"100"}],"byTM":[{"Level":"1","Name":"Work Up","Type":"Normal","Category":"status","Power":"—","Accuracy":"—"},{"Level":"6","Name":"Toxic","Type":"Poison","Category":"status","Power":"—","Accuracy":"90"},{"Level":"7","Name":"Hail","Type":"Ice","Category":"status","Power":"—","Accuracy":"—"},{"Level":"10","Name":"Hidden Power","Type":"Normal","Category":"special","Power":"60","Accuracy":"100"},{"Level":"12","Name":"Taunt","Type":"Dark","Category":"status","Power":"—","Accuracy":"100"},{"Level":"13","Name":"Ice Beam","Type":"Ice","Category":"special","Power":"90","Accuracy":"100"},{"Level":"14","Name":"Blizzard","Type":"Ice","Category":"special","Power":"110","Accuracy":"70"},{"Level":"15","Name":"Hyper Beam","Type":"Normal","Category":"special","Power":"150","Accuracy":"90"},{"Level":"17","Name":"Protect","Type":"Normal","Category":"status","Power":"—","Accuracy":"—"},{"Level":"18","Name":"Rain Dance","Type":"Water","Category":"status","Power":"—","Accuracy":"—"},{"Level":"21","Name":"Frustration","Type":"Normal","Category":"physical","Power":"—","Accuracy":"100"},{"Level":"27","Name":"Return","Type":"Normal","Category":"physical","Power":"—","Accuracy":"100"},{"Level":"32","Name":"Double Team","Type":"Normal","Category":"status","Power":"—","Accuracy":"—"},{"Level":"40","Name":"Aerial Ace","Type":"Flying","Category":"physical","Power":"60","Accuracy":"∞"},{"Level":"42","Name":"Facade","Type":"Normal","Category":"physical","Power":"70","Accuracy":"100"},{"Level":"44","Name":"Rest","Type":"Psychic","Category":"status","Power":"—","Accuracy":"—"},{"Level":"45","Name":"Attract","Type":"Normal","Category":"status","Power":"—","Accuracy":"100"},{"Level":"48","Name":"Round","Type":"Normal","Category":"special","Power":"60","Accuracy":"100"},{"Level":"54","Name":"False Swipe","Type":"Normal","Category":"physical","Power":"40","Accuracy":"100"},{"Level":"55","Name":"Scald","Type":"Water","Category":"special","Power":"80","Accuracy":"100"},{"Level":"56","Name":"Fling","Type":"Dark","Category":"physical","Power":"—","Accuracy":"100"},{"Level":"67","Name":"Smart Strike","Type":"Steel","Category":"physical","Power":"70","Accuracy":"—"},{"Level":"68","Name":"Giga Impact","Type":"Normal","Category":"physical","Power":"150","Accuracy":"90"},{"Level":"75","Name":"Swords Dance","Type":"Normal","Category":"status","Power":"—","Accuracy":"—"},{"Level":"81","Name":"X-Scissor","Type":"Bug","Category":"physical","Power":"80","Accuracy":"100"},{"Level":"82","Name":"Dragon Tail","Type":"Dragon","Category":"physical","Power":"60","Accuracy":"90"},{"Level":"86","Name":"Grass Knot","Type":"Grass","Category":"special","Power":"—","Accuracy":"100"},{"Level":"87","Name":"Swagger","Type":"Normal","Category":"status","Power":"—","Accuracy":"85"},{"Level":"88","Name":"Sleep Talk","Type":"Normal","Category":"status","Power":"—","Accuracy":"—"},{"Level":"90","Name":"Substitute","Type":"Normal","Category":"status","Power":"—","Accuracy":"—"},{"Level":"94","Name":"Surf","Type":"Water","Category":"special","Power":"90","Accuracy":"100"},{"Level":"98","Name":"Waterfall","Type":"Water","Category":"physical","Power":"80","Accuracy":"100"},{"Level":"100","Name":"Confide","Type":"Normal","Category":"status","Power":"—","Accuracy":"—"}]},"location":{"BlackWhite":["Evolve Oshawott/Dewott"],"Black 2White 2":["Trade/migrate from another game"],"XY":["Trade/migrate from another game"],"Omega RubyAlpha Sapphire":["Evolve Oshawott/Dewott"],"SunMoon":["Trade/migrate from another game"]},"imageUrl":"https://img.pokemondb.net/artwork/samurott.jpg"}